MANIFEST.in
README.rst
setup.cfg
setup.py
mlpg_c/__init__.py
mlpg_c/mlpg_c.pyx
mlpg_c.egg-info/PKG-INFO
mlpg_c.egg-info/SOURCES.txt
mlpg_c.egg-info/dependency_links.txt
mlpg_c.egg-info/requires.txt
mlpg_c.egg-info/top_level.txt
src/mlpg_sub_c.c
src/mlpg_sub_c.h