Metadata-Version: 1.0
Name: mlpg-c
Version: 0.0.6.dev1
Summary: Maximum Likelihood Parameter Generation (MLPG) implementation in C for Python
Home-page: https://github.com/patrickltobing/mlpg_c
Author: Patrick Lumban Tobing
Author-email: patrickltobing@gmail.com
License: UNKNOWN
Keywords: maximum likelihood parameter generation,mlpg
Platform: UNKNOWN
